README.rst
setup.py
zxcvbn/__init__.py
zxcvbn/__main__.py
zxcvbn/adjacency_graphs.py
zxcvbn/feedback.py
zxcvbn/frequency_lists.py
zxcvbn/matching.py
zxcvbn/scoring.py
zxcvbn/time_estimates.py
zxcvbn.egg-info/PKG-INFO
zxcvbn.egg-info/SOURCES.txt
zxcvbn.egg-info/dependency_links.txt
zxcvbn.egg-info/entry_points.txt
zxcvbn.egg-info/top_level.txt